[
	{
		"header": "동탄 반송 5 스테이션 신규 설치 안내",
		"contents": "동탄 반송 5 스테이션이 추가되었습니다"
	},
	{
		"header": "버전 1.1.0 업데이트 안내",
		"contents": "새로운 기능들이 추가되었습니다."
	},
	{
		"header": "포인트 지급 정책 변경 안내",
		"contents": "포인트 지급 정책이 변경되었습니다."
	},
	{
		"header": "포인트 지급 정책 변경 안내",
		"contents": "포인트 지급 정책이 변경되었습니다."
	},
	{
		"header": "포인트 지급 정책 변경 안내",
		"contents": "포인트 지급 정책이 변경되었습니다."
	},
	{
		"header": "포인트 지급 정책 변경 안내",
		"contents": "포인트 지급 정책이 변경되었습니다."
	},
	{
		"header": "포인트 지급 정책 변경 안내",
		"contents": "포인트 지급 정책이 변경되었습니다."
	}
]
